stl_reducer-0.1.4.dist-info/METADATA
stl_reducer-0.1.4.dist-info/WHEEL
stl_reducer/__init__.py
stl_reducer/__init__.pyi
stl_reducer/py.typed
stl_reducer/stl_reducer.cp39-win_amd64.pyd
stl_reducer-0.1.4.dist-info/RECORD
